jltool
