Metadata-Version: 1.1
Name: jltool
Version: 1.1.0
Summary: Tools for inspecting, comparing, & cleaning JSON-Lines files
Home-page: https://github.com/cathalgarvey/jltool
Author: Cathal Garvey
Author-email: cathalgarvey@cathalgarvey.me
License: GNU Affero General Public License v3
Platform: UNKNOWN
Classifier: License :: OSI Approved :: GNU Affero General Public License v3 or later (AGPLv3+)
Classifier: Development Status :: 3 - Alpha
Classifier: Topic :: Utilities
Classifier: Environment :: Console
Classifier: Natural Language :: English
Classifier: Programming Language :: Python
Classifier: Programming Language :: Python :: 3.3
Classifier: Programming Language :: Python :: 3.4
Classifier: Programming Language :: Python :: 3.5
